myemail/__init__.py
myemail/myemail.py
myemail-0.9.0.dist-info/LICENSE
myemail-0.9.0.dist-info/METADATA
myemail-0.9.0.dist-info/WHEEL
myemail-0.9.0.dist-info/RECORD
