Metadata-Version: 2.1
Name: myemail
Version: 0.9.0
Summary: A simple package to send emails with python
Home-page: https://github.com/tct123/myemail
License: MIT
Author: tct123
Author-email: 42028373+tct123@users.noreply.github.com
Requires-Python: >=3.8,<4.0
Classifier: License :: OSI Approved :: MIT License
Classifier: Programming Language :: Python :: 3
Classifier: Programming Language :: Python :: 3.8
Classifier: Programming Language :: Python :: 3.9
Classifier: Programming Language :: Python :: 3.10
Classifier: Programming Language :: Python :: 3.11
Classifier: Programming Language :: Python :: 3.12
Project-URL: Repository, https://github.com/tct123/myemail
